netbox_routing_complex/__init__.py
netbox_routing_complex/constants.py
netbox_routing_complex/filtersets.py
netbox_routing_complex/forms.py
netbox_routing_complex/models.py
netbox_routing_complex/navigation.py
netbox_routing_complex/tables.py
netbox_routing_complex/urls.py
netbox_routing_complex/views.py
netbox_routing_complex/api/__init__.py
netbox_routing_complex/api/serializers.py
netbox_routing_complex/api/urls.py
netbox_routing_complex/api/views.py
netbox_routing_complex/migrations/0001_initial.py
netbox_routing_complex/migrations/0002_bgppeergroup.py
netbox_routing_complex/migrations/0003_bgppeer_device.py
netbox_routing_complex/migrations/0004_alter_bgppeer_device.py
netbox_routing_complex/migrations/0005_vni_vxlan.py
netbox_routing_complex/migrations/0006_alter_vni_unique_together.py
netbox_routing_complex/migrations/0007_isisconfig.py
netbox_routing_complex/migrations/0008_alter_isisconfig_options_and_more.py
netbox_routing_complex/migrations/0009_bgpglobalconfig.py
netbox_routing_complex/migrations/0010_staticroute.py
netbox_routing_complex/migrations/0011_alter_staticroute_subnet.py
netbox_routing_complex/migrations/__init__.py
netbox_routing_complex/templates/netbox_routing_complex/bfdconfig.html
netbox_routing_complex/templates/netbox_routing_complex/bgpglobalconfig.html
netbox_routing_complex/templates/netbox_routing_complex/bgppeer.html
netbox_routing_complex/templates/netbox_routing_complex/bgppeergroup.html
netbox_routing_complex/templates/netbox_routing_complex/bgpsessionconfig.html
netbox_routing_complex/templates/netbox_routing_complex/isisconfig.html
netbox_routing_complex/templates/netbox_routing_complex/staticroute.html
netbox_routing_complex/templates/netbox_routing_complex/vni.html
netbox_routing_complex/templates/netbox_routing_complex/vxlan.html
netbox_routing_complex-0.2.152.dist-info/METADATA
netbox_routing_complex-0.2.152.dist-info/WHEEL
netbox_routing_complex-0.2.152.dist-info/top_level.txt
netbox_routing_complex-0.2.152.dist-info/RECORD
