Metadata-Version: 2.4
Name: netbox-routing-complex
Version: 0.2.152
Summary: Add your description here
Requires-Python: >=3.12
Requires-Dist: certifi>=2025.10.5
Requires-Dist: django-tables2>=2.7.5
Requires-Dist: djangorestframework>=3.16.1
